napari_boardgame_maker/__init__.py
napari_boardgame_maker/_sample_data.py
napari_boardgame_maker/_widget.py
napari_boardgame_maker/napari.yaml
napari_boardgame_maker/_tests/__init__.py
napari_boardgame_maker/_tests/test_widget.py
napari_boardgame_maker-0.0.2.dist-info/LICENSE
napari_boardgame_maker-0.0.2.dist-info/METADATA
napari_boardgame_maker-0.0.2.dist-info/WHEEL
napari_boardgame_maker-0.0.2.dist-info/entry_points.txt
napari_boardgame_maker-0.0.2.dist-info/top_level.txt
napari_boardgame_maker-0.0.2.dist-info/RECORD
